unifipy/__init__.py
unifipy/unifi.py
unifipy/unifipy.py
unifipy-1.0.4.dist-info/LICENSE
unifipy-1.0.4.dist-info/METADATA
unifipy-1.0.4.dist-info/WHEEL
unifipy-1.0.4.dist-info/top_level.txt
unifipy-1.0.4.dist-info/RECORD
