Metadata-Version: 2.1
Name: unifipy
Version: 1.0.4
Summary: Unifi Python API
Home-page: https://github.com/fronbasal/unifipy
Author: Daniel Malik
Author-email: mail@fronbasal.de
License: MIT License
Platform: UNKNOWN
Classifier: Programming Language :: Python :: 3
Classifier: License :: OSI Approved :: MIT License
Classifier: Operating System :: OS Independent
Requires-Python: >=3.6
Requires-Dist: requests
